omymodels/__init__.py
omymodels/cli.py
omymodels/converter.py
omymodels/errors.py
omymodels/from_ddl.py
omymodels/generation/__init__.py
omymodels/generation/base.py
omymodels/generation/datamodel_base.py
omymodels/generation/orm_base.py
omymodels/generators.py
omymodels/helpers.py
omymodels/logic.py
omymodels/models/dataclass/core.py
omymodels/models/dataclass/dataclass.jinja2
omymodels/models/dataclass/templates.py
omymodels/models/dataclass/types.py
omymodels/models/enum/core.py
omymodels/models/enum/enum.jinja2
omymodels/models/enum/template.jinja2
omymodels/models/gino/core.py
omymodels/models/gino/gino.jinja2
omymodels/models/gino/templates.py
omymodels/models/gino/types.py
omymodels/models/openapi3/__init__.py
omymodels/models/openapi3/core.py
omymodels/models/pydal/core.py
omymodels/models/pydal/pydal.jinja2
omymodels/models/pydal/templates.py
omymodels/models/pydantic/core.py
omymodels/models/pydantic/pydantic.jinja2
omymodels/models/pydantic/templates.py
omymodels/models/pydantic/types.py
omymodels/models/pydantic_v2/__init__.py
omymodels/models/pydantic_v2/core.py
omymodels/models/pydantic_v2/pydantic_v2.jinja2
omymodels/models/pydantic_v2/templates.py
omymodels/models/pydantic_v2/types.py
omymodels/models/sqlalchemy/core.py
omymodels/models/sqlalchemy/sqlalchemy.jinja2
omymodels/models/sqlalchemy/templates.py
omymodels/models/sqlalchemy/types.py
omymodels/models/sqlalchemy_core/core.py
omymodels/models/sqlalchemy_core/sqlalchemy_core.jinja2
omymodels/models/sqlalchemy_core/templates.py
omymodels/models/sqlalchemy_v2/__init__.py
omymodels/models/sqlalchemy_v2/core.py
omymodels/models/sqlalchemy_v2/sqlalchemy_v2.jinja2
omymodels/models/sqlalchemy_v2/templates.py
omymodels/models/sqlalchemy_v2/types.py
omymodels/models/sqlmodel/core.py
omymodels/models/sqlmodel/sqlmodel.jinja2
omymodels/models/sqlmodel/templates.py
omymodels/models/sqlmodel/types.py
omymodels/models/tortoise/core.py
omymodels/models/tortoise/pydal.jinja2
omymodels-1.0.0.dist-info/METADATA
omymodels-1.0.0.dist-info/WHEEL
omymodels-1.0.0.dist-info/entry_points.txt
omymodels-1.0.0.dist-info/licenses/LICENSE
omymodels-1.0.0.dist-info/RECORD
