Metadata-Version: 2.4
Name: omymodels
Version: 1.0.0
Summary: O! My Models (omymodels) is a library to generate Python Models for SQLAlchemy (ORM & Core), SQLModel, GinoORM, Pydantic, Pydal tables & Python Dataclasses from SQL DDL. And convert one models to another.
License: MIT
License-File: LICENSE
Author: Iuliia Volkova
Author-email: xnuinside@gmail.com
Requires-Python: >=3.9,<4.0
Classifier: License :: OSI Approved :: MIT License
Classifier: Programming Language :: PL/SQL
Classifier: Programming Language :: Python :: 3
Classifier: Programming Language :: Python :: 3.9
Classifier: Programming Language :: Python :: 3.10
Classifier: Programming Language :: Python :: 3.11
Classifier: Programming Language :: Python :: 3.12
Classifier: Programming Language :: Python :: 3.13
Classifier: Programming Language :: Python :: 3.14
Classifier: Programming Language :: SQL
Classifier: Topic :: Software Development
Classifier: Topic :: Software Development :: Code Generators
Classifier: Topic :: Software Development :: Libraries
Classifier: Topic :: Software Development :: Libraries :: Python Modules
Classifier: Topic :: Utilities
Requires-Dist: Jinja2 (>=3.0.1,<4.0.0)
Requires-Dist: py-models-parser (>=1.0.0,<2.0.0)
Requires-Dist: pydantic (>=1.8.2,<3.0.0)
Requires-Dist: simple-ddl-parser (>=1.0.0,<2.0.0)
Requires-Dist: table-meta (>=0.1.5)
Project-URL: Homepage, https://github.com/xnuinside/omymodels
Project-URL: Repository, https://github.com/xnuinside/omymodels
